{
  "profile": {
    "name": "Theuss.devs",
    "handle": "@theuss.devs",
    "bio": "Developer & Designer"
  },
  "links": [
    {
      "id": "instagram",
      "label": "Instagram",
      "url": "",
      "icon": "instagram",
      "active": false
    },
    {
      "id": "tiktok",
      "label": "TikTok",
      "url": "",
      "icon": "tiktok",
      "active": false
    },
    {
      "id": "youtube",
      "label": "YouTube",
      "url": "",
      "icon": "youtube",
      "active": false
    },
    {
      "id": "github",
      "label": "GitHub",
      "url": "",
      "icon": "github",
      "active": false
    },
    {
      "id": "linkedin",
      "label": "LinkedIn",
      "url": "",
      "icon": "linkedin",
      "active": false
    },
    {
      "id": "behance",
      "label": "Behance",
      "url": "",
      "icon": "behance",
      "active": false
    },
    {
      "id": "discord",
      "label": "Discord",
      "url": "",
      "icon": "discord",
      "active": false
    },
    {
      "id": "whatsapp",
      "label": "WhatsApp",
      "url": "",
      "icon": "whatsapp",
      "active": false
    },
    {
      "id": "portfolio",
      "label": "Portfólio",
      "url": "",
      "icon": "portfolio",
      "active": false
    }
  ]
}